pyambit/__init__.py
pyambit/ambit_deco.py
pyambit/datamodel.py
pyambit/nexus_parser.py
pyambit/nexus_spectra.py
pyambit/nexus_writer.py
pyambit/solr_writer.py
pyambit-0.0.2.dist-info/LICENSE
pyambit-0.0.2.dist-info/METADATA
pyambit-0.0.2.dist-info/WHEEL
pyambit-0.0.2.dist-info/RECORD
